pipOddEven/__init__.py
pipOddEven/main.py
pipoddeven-0.1.1.dist-info/licenses/LICENSE
pipoddeven-0.1.1.dist-info/METADATA
pipoddeven-0.1.1.dist-info/WHEEL
pipoddeven-0.1.1.dist-info/top_level.txt
pipoddeven-0.1.1.dist-info/RECORD
