Metadata-Version: 2.4
Name: pipOddEven
Version: 0.1.1
Summary: A simple library to check if a number is odd or even.
Author-email: Shiv <bshivkiran120602@gmail.com>
Project-URL: Homepage, https://github.com/Shiv-Kiran/pipOddEven
Project-URL: Issues, https://github.com/Shiv-Kiran/pipOddEven/issues
Classifier: Programming Language :: Python :: 3
Classifier: License :: OSI Approved :: MIT License
Classifier: Operating System :: OS Independent
Requires-Python: >=3.7
License-File: LICENSE
Dynamic: license-file
